graph_nx_tools-1.0.0.dist-info/DESCRIPTION.rst
graph_nx_tools-1.0.0.dist-info/METADATA
graph_nx_tools-1.0.0.dist-info/RECORD
graph_nx_tools-1.0.0.dist-info/WHEEL
graph_nx_tools-1.0.0.dist-info/metadata.json
graph_nx_tools-1.0.0.dist-info/top_level.txt
graph_tools/__init__.py
graph_tools/epidemics_utils.py
graph_tools/graph_path_utils.py
graph_tools/graph_preprocessing.py
graph_tools/graph_statistics.py
graph_tools/graph_visualizations.py
graph_tools/netsci_utils.py
graph_tools/null_models.py
